vibing/__init__.py
vibing/py.typed
vibing/calibration/__init__.py
vibing/calibration/cli.py
vibing/calibration/distortion_checker.py
vibing/geometry/__init__.py
vibing/geometry/depth.py
vibing/geometry/scale.py
vibing/optimization/__init__.py
vibing/optimization/gradient_free.py
vibing/optimization/lbfgsb.py
vibing/plotting/__init__.py
vibing/plotting/core.py
vibing/pose/__init__.py
vibing/pose/analysis.py
vibing/pose/hull.py
vibing/pose/interpolate.py
vibing/pose/region.py
vibing/powerwell/__init__.py
vibing/sleap_convert/__init__.py
vibing/sleap_convert/cli.py
vibing/sleap_convert/slp_to_yaml.py
vibing/undistortion/__init__.py
vibing/video/__init__.py
vibing/video/batch.py
vibing/video/info.py
vibing/video/parallel.py
vibing-0.5.0.dist-info/METADATA
vibing-0.5.0.dist-info/WHEEL
vibing-0.5.0.dist-info/entry_points.txt
vibing-0.5.0.dist-info/licenses/LICENSE
vibing-0.5.0.dist-info/RECORD
