Metadata-Version: 2.4
Name: vibing
Version: 0.5.0
Summary: A collection of small but useful tools for scientific publications and projects
Project-URL: Homepage, https://github.com/LeoMeow123/vibes
Project-URL: Repository, https://github.com/LeoMeow123/vibes
Project-URL: Issues, https://github.com/LeoMeow123/vibes/issues
Author: LeoMeow123
License-Expression: MIT
License-File: LICENSE
Keywords: optimization,plotting,scientific,sleap,tools
Classifier: Development Status :: 3 - Alpha
Classifier: Intended Audience :: Science/Research
Classifier: License :: OSI Approved :: MIT License
Classifier: Programming Language :: Python :: 3
Classifier: Programming Language :: Python :: 3.12
Classifier: Topic :: Scientific/Engineering
Requires-Python: >=3.12
Requires-Dist: matplotlib>=3.8.0
Requires-Dist: numpy>=1.26.0
Requires-Dist: scipy>=1.11.0
Provides-Extra: all
Requires-Dist: opencv-python>=4.8.0; extra == 'all'
Requires-Dist: pytest>=7.4.0; extra == 'all'
Requires-Dist: pyyaml>=6.0; extra == 'all'
Requires-Dist: ruff>=0.1.0; extra == 'all'
Requires-Dist: shapely>=2.0.0; extra == 'all'
Requires-Dist: sleap-io>=0.2.0; extra == 'all'
Provides-Extra: calibration
Requires-Dist: opencv-python>=4.8.0; extra == 'calibration'
Provides-Extra: dev
Requires-Dist: pytest>=7.4.0; extra == 'dev'
Requires-Dist: ruff>=0.1.0; extra == 'dev'
Provides-Extra: geometry
Requires-Dist: shapely>=2.0.0; extra == 'geometry'
Provides-Extra: sleap
Requires-Dist: pyyaml>=6.0; extra == 'sleap'
Requires-Dist: sleap-io>=0.2.0; extra == 'sleap'
Provides-Extra: video
Requires-Dist: opencv-python>=4.8.0; extra == 'video'
